README.rst
setup.py
django_monkeytranslate.egg-info/PKG-INFO
django_monkeytranslate.egg-info/SOURCES.txt
django_monkeytranslate.egg-info/dependency_links.txt
django_monkeytranslate.egg-info/not-zip-safe
django_monkeytranslate.egg-info/requires.txt
django_monkeytranslate.egg-info/top_level.txt
monkeytranslate/__init__.py
monkeytranslate/apps.py
monkeytranslate/conf.py
monkeytranslate/utils.py