Metadata-Version: 1.1
Name: django-monkeytranslate
Version: 0.1.1
Summary: Monkeypatch django do-translation
Home-page: https://github.com/ashwoods/django-monkeytranslate
Author: Ashley Camba Garrido
Author-email: ashwoods@gmail.com
License: BSD
Platform: UNKNOWN
Classifier: Development Status :: 4 - Beta
Classifier: Intended Audience :: Developers
Classifier: License :: OSI Approved :: BSD License
Classifier: Operating System :: OS Independent
Classifier: Programming Language :: Python
Classifier: Programming Language :: Python :: 2.7
Classifier: Programming Language :: Python :: 3.4
Classifier: Programming Language :: Python :: 3.5
Classifier: Topic :: Utilities
